[
  { "name": "Python", "snippet": "def greet(name):\n    print(f\"Hello, {name}!\")\n\nif __name__ == \"__main__\":\n    greet(\"World\")", "paradigm": "Multi", "typing": "Dynamic", "year": 1991 },
  { "name": "Java", "snippet": "public class Main {\n    public static void main(String[] args) {\n        System.out.println(\"Hello World\");\n    }\n}", "paradigm": "OO", "typing": "Static", "year": 1995 },
  { "name": "JavaScript", "snippet": "const greet = (name) => {\n    console.log(`Hello ${name}`);\n};\ngreet('World');", "paradigm": "Multi", "typing": "Dynamic", "year": 1995 },
  { "name": "C++", "snippet": "#include <iostream>\n\nint main() {\n    std::cout << \"Hello World\" << std::endl;\n    return 0;\n}", "paradigm": "Multi", "typing": "Static", "year": 1985 },
  { "name": "C#", "snippet": "using System;\n\nclass Program {\n    static void Main() {\n        Console.WriteLine(\"Hello World\");\n    }\n}", "paradigm": "Multi", "typing": "Static", "year": 2000 },
  { "name": "C", "snippet": "#include <stdio.h>\n\nint main() {\n    printf(\"Hello, World!\\n\");\n    return 0;\n}", "paradigm": "Imperative", "typing": "Static", "year": 1972 },
  { "name": "PHP", "snippet": "<?php\n    echo \"Hello World\";\n?>", "paradigm": "Multi", "typing": "Dynamic", "year": 1995 },
  { "name": "Swift", "snippet": "import Swift\nprint(\"Hello, World!\")", "paradigm": "Multi", "typing": "Static", "year": 2014 },
  { "name": "Go", "snippet": "package main\nimport \"fmt\"\n\nfunc main() {\n    fmt.Println(\"Hello World\")\n}", "paradigm": "Concurrent", "typing": "Static", "year": 2009 },
  { "name": "Rust", "snippet": "fn main() {\n    println!(\"Hello World\");\n}", "paradigm": "Multi", "typing": "Static", "year": 2010 },
  { "name": "Ruby", "snippet": "puts \"Hello World\"", "paradigm": "Multi", "typing": "Dynamic", "year": 1995 },
  { "name": "Kotlin", "snippet": "fun main() {\n    println(\"Hello World\")\n}", "paradigm": "Multi", "typing": "Static", "year": 2011 },
  { "name": "TypeScript", "snippet": "const msg: string = \"Hello World\";\nconsole.log(msg);", "paradigm": "Multi", "typing": "Static", "year": 2012 },
  { "name": "Scala", "snippet": "object Hello extends App {\n  println(\"Hello, World!\")\n}", "paradigm": "Multi", "typing": "Static", "year": 2004 },
  { "name": "Perl", "snippet": "print \"Hello World\\n\";", "paradigm": "Multi", "typing": "Dynamic", "year": 1987 },
  { "name": "Lua", "snippet": "print(\"Hello World\")", "paradigm": "Multi", "typing": "Dynamic", "year": 1993 },
  { "name": "Haskell", "snippet": "main = putStrLn \"Hello World\"", "paradigm": "Functional", "typing": "Static", "year": 1990 },
  { "name": "R", "snippet": "print(\"Hello World\")", "paradigm": "Multi", "typing": "Dynamic", "year": 1993 },
  { "name": "MATLAB", "snippet": "disp('Hello World')", "paradigm": "Multi", "typing": "Dynamic", "year": 1984 },
  { "name": "Assembly", "snippet": "section .data\nmsg db 'Hello World',0xa\nlen equ $ - msg\nsection .text\n    global _start\n_start:\n    mov edx,len\n    mov ecx,msg\n    mov ebx,1\n    mov eax,4\n    int 0x80", "paradigm": "Imperative", "typing": "Untyped", "year": 1949 },
  { "name": "COBOL", "snippet": "IDENTIFICATION DIVISION.\nPROGRAM-ID. HELLO-WORLD.\nPROCEDURE DIVISION.\n    DISPLAY 'Hello World'.\n    STOP RUN.", "paradigm": "Imperative", "typing": "Static", "year": 1959 },
  { "name": "Fortran", "snippet": "PROGRAM HELLO\n  PRINT *, 'Hello World'\nEND PROGRAM HELLO", "paradigm": "Imperative", "typing": "Static", "year": 1957 },
  { "name": "Pascal", "snippet": "program Hello;\nbegin\n  writeln('Hello World');\nend.", "paradigm": "Imperative", "typing": "Static", "year": 1970 },
  { "name": "Basic", "snippet": "10 PRINT \"Hello World\"\n20 END", "paradigm": "Imperative", "typing": "Dynamic", "year": 1964 },
  { "name": "Lisp", "snippet": "(print \"Hello World\")", "paradigm": "Functional", "typing": "Dynamic", "year": 1958 },
  { "name": "Dart", "snippet": "void main() {\n  print('Hello World');\n}", "paradigm": "Multi", "typing": "Static", "year": 2011 },
  { "name": "Elixir", "snippet": "IO.puts \"Hello World\"", "paradigm": "Functional", "typing": "Dynamic", "year": 2011 },
  { "name": "Julia", "snippet": "println(\"Hello World\")", "paradigm": "Multi", "typing": "Dynamic", "year": 2012 },
  { "name": "Brainfuck", "snippet": "++++++++[>++++[>++>+++>+++>+<<<<-]>+>+>->>+[<]<-]>>.>---.+++++++..+++.>>.<-.<.+++.------.--------.>>+.>++.", "paradigm": "Esoteric", "typing": "Untyped", "year": 1993 },
  { "name": "SQL", "snippet": "SELECT 'Hello World';", "paradigm": "Declarative", "typing": "Static", "year": 1974 }
]